<?xml version="1.0" encoding="UTF-8"?><record_update>
    <sys_choice action="DELETE" field="state" table="x_58872_needit_needit" version="3">
        <sys_choice action="INSERT_OR_UPDATE">
            <dependent_value/>
            <element>state</element>
            <hint/>
            <inactive>false</inactive>
            <label>Requested</label>
            <language>en</language>
            <name>x_58872_needit_needit</name>
            <sequence>0</sequence>
            <sys_created_by>admin</sys_created_by>
            <sys_created_on>2017-01-26 20:14:39</sys_created_on>
            <sys_domain>global</sys_domain>
            <sys_domain_path>/</sys_domain_path>
            <sys_id>e0b229350fa03200cd674f8ce1050ea9</sys_id>
            <sys_mod_count>0</sys_mod_count>
            <sys_updated_by>admin</sys_updated_by>
            <sys_updated_on>2017-01-26 20:14:39</sys_updated_on>
            <value>13</value>
        </sys_choice>
        <sys_choice action="INSERT_OR_UPDATE">
            <dependent_value/>
            <element>state</element>
            <hint/>
            <inactive>false</inactive>
            <label>Awaiting Approval</label>
            <language>en</language>
            <name>x_58872_needit_needit</name>
            <sequence>1</sequence>
            <sys_created_by>admin</sys_created_by>
            <sys_created_on>2017-01-26 20:14:39</sys_created_on>
            <sys_domain>global</sys_domain>
            <sys_domain_path>/</sys_domain_path>
            <sys_id>ecb229350fa03200cd674f8ce1050eaa</sys_id>
            <sys_mod_count>0</sys_mod_count>
            <sys_updated_by>admin</sys_updated_by>
            <sys_updated_on>2017-01-26 20:14:39</sys_updated_on>
            <value>14</value>
        </sys_choice>
        <sys_choice action="INSERT_OR_UPDATE">
            <dependent_value/>
            <element>state</element>
            <hint/>
            <inactive>false</inactive>
            <label>Approved</label>
            <language>en</language>
            <name>x_58872_needit_needit</name>
            <sequence>2</sequence>
            <sys_created_by>admin</sys_created_by>
            <sys_created_on>2017-01-26 20:14:39</sys_created_on>
            <sys_domain>global</sys_domain>
            <sys_domain_path>/</sys_domain_path>
            <sys_id>28b229350fa03200cd674f8ce1050eac</sys_id>
            <sys_mod_count>0</sys_mod_count>
            <sys_updated_by>admin</sys_updated_by>
            <sys_updated_on>2017-01-26 20:14:39</sys_updated_on>
            <value>15</value>
        </sys_choice>
        <sys_choice action="INSERT_OR_UPDATE">
            <dependent_value/>
            <element>state</element>
            <hint/>
            <inactive>false</inactive>
            <label>Awaiting Feedback</label>
            <language>en</language>
            <name>x_58872_needit_needit</name>
            <sequence>3</sequence>
            <sys_created_by>admin</sys_created_by>
            <sys_created_on>2017-01-26 20:14:39</sys_created_on>
            <sys_domain>global</sys_domain>
            <sys_domain_path>/</sys_domain_path>
            <sys_id>60b229350fa03200cd674f8ce1050eae</sys_id>
            <sys_mod_count>0</sys_mod_count>
            <sys_updated_by>admin</sys_updated_by>
            <sys_updated_on>2017-01-26 20:14:39</sys_updated_on>
            <value>16</value>
        </sys_choice>
        <sys_choice action="INSERT_OR_UPDATE">
            <dependent_value/>
            <element>state</element>
            <hint/>
            <inactive>false</inactive>
            <label>Closed Complete</label>
            <language>en</language>
            <name>x_58872_needit_needit</name>
            <sequence>4</sequence>
            <sys_created_by>admin</sys_created_by>
            <sys_created_on>2017-01-26 20:14:39</sys_created_on>
            <sys_domain>global</sys_domain>
            <sys_domain_path>/</sys_domain_path>
            <sys_id>a8b229350fa03200cd674f8ce1050eaf</sys_id>
            <sys_mod_count>0</sys_mod_count>
            <sys_updated_by>admin</sys_updated_by>
            <sys_updated_on>2017-01-26 20:14:39</sys_updated_on>
            <value>3</value>
        </sys_choice>
        <sys_choice action="INSERT_OR_UPDATE">
            <dependent_value/>
            <element>state</element>
            <hint/>
            <inactive>false</inactive>
            <label>Withdrawn</label>
            <language>en</language>
            <name>x_58872_needit_needit</name>
            <sequence>5</sequence>
            <sys_created_by>admin</sys_created_by>
            <sys_created_on>2017-01-26 20:14:39</sys_created_on>
            <sys_domain>global</sys_domain>
            <sys_domain_path>/</sys_domain_path>
            <sys_id>a0b229350fa03200cd674f8ce1050eb1</sys_id>
            <sys_mod_count>0</sys_mod_count>
            <sys_updated_by>admin</sys_updated_by>
            <sys_updated_on>2017-01-26 20:14:39</sys_updated_on>
            <value>8</value>
        </sys_choice>
        <sys_choice_set action="INSERT_OR_UPDATE">
            <element>state</element>
            <name>x_58872_needit_needit</name>
            <sys_class_name>sys_choice_set</sys_class_name>
            <sys_created_by>admin</sys_created_by>
            <sys_created_on>2017-01-26 20:14:39</sys_created_on>
            <sys_id>776049e5dbaf5b009d7831d0ef961901</sys_id>
            <sys_mod_count>1</sys_mod_count>
            <sys_name>state</sys_name>
            <sys_package display_value="NeedIt" source="x_58872_needit">6ead8e780f603200cd674f8ce1050ed1</sys_package>
            <sys_policy/>
            <sys_scope display_value="NeedIt">6ead8e780f603200cd674f8ce1050ed1</sys_scope>
            <sys_update_name>sys_choice_x_58872_needit_needit_state</sys_update_name>
            <sys_updated_by>admin</sys_updated_by>
            <sys_updated_on>2017-01-26 20:14:39</sys_updated_on>
        </sys_choice_set>
    </sys_choice>
<sys_update_version action="INSERT_OR_UPDATE">
        <action>DELETE</action>
        <application display_value="NeedIt">6ead8e780f603200cd674f8ce1050ed1</application>
        <file_path/>
        <instance_id>432ae26ddb3613400e785d00cf961945</instance_id>
        <instance_name>dev61794</instance_name>
        <name>sys_choice_x_58872_needit_needit_state</name>
        <payload><![CDATA[<?xml version="1.0" encoding="UTF-8"?><record_update>
    <sys_choice action="INSERT_OR_UPDATE" field="state" table="x_58872_needit_needit" version="3">
        <sys_choice action="INSERT_OR_UPDATE">
            <dependent_value/>
            <element>state</element>
            <hint/>
            <inactive>false</inactive>
            <label>Requested</label>
            <language>en</language>
            <name>x_58872_needit_needit</name>
            <sequence>0</sequence>
            <sys_created_by>admin</sys_created_by>
            <sys_created_on>2017-01-26 20:14:39</sys_created_on>
            <sys_domain>global</sys_domain>
            <sys_domain_path>/</sys_domain_path>
            <sys_id>e0b229350fa03200cd674f8ce1050ea9</sys_id>
            <sys_mod_count>0</sys_mod_count>
            <sys_updated_by>admin</sys_updated_by>
            <sys_updated_on>2017-01-26 20:14:39</sys_updated_on>
            <value>13</value>
        </sys_choice>
        <sys_choice action="INSERT_OR_UPDATE">
            <dependent_value/>
            <element>state</element>
            <hint/>
            <inactive>false</inactive>
            <label>Awaiting Approval</label>
            <language>en</language>
            <name>x_58872_needit_needit</name>
            <sequence>1</sequence>
            <sys_created_by>admin</sys_created_by>
            <sys_created_on>2017-01-26 20:14:39</sys_created_on>
            <sys_domain>global</sys_domain>
            <sys_domain_path>/</sys_domain_path>
            <sys_id>ecb229350fa03200cd674f8ce1050eaa</sys_id>
            <sys_mod_count>0</sys_mod_count>
            <sys_updated_by>admin</sys_updated_by>
            <sys_updated_on>2017-01-26 20:14:39</sys_updated_on>
            <value>14</value>
        </sys_choice>
        <sys_choice action="INSERT_OR_UPDATE">
            <dependent_value/>
            <element>state</element>
            <hint/>
            <inactive>false</inactive>
            <label>Approved</label>
            <language>en</language>
            <name>x_58872_needit_needit</name>
            <sequence>2</sequence>
            <sys_created_by>admin</sys_created_by>
            <sys_created_on>2017-01-26 20:14:39</sys_created_on>
            <sys_domain>global</sys_domain>
            <sys_domain_path>/</sys_domain_path>
            <sys_id>28b229350fa03200cd674f8ce1050eac</sys_id>
            <sys_mod_count>0</sys_mod_count>
            <sys_updated_by>admin</sys_updated_by>
            <sys_updated_on>2017-01-26 20:14:39</sys_updated_on>
            <value>15</value>
        </sys_choice>
        <sys_choice action="INSERT_OR_UPDATE">
            <dependent_value/>
            <element>state</element>
            <hint/>
            <inactive>false</inactive>
            <label>Awaiting Feedback</label>
            <language>en</language>
            <name>x_58872_needit_needit</name>
            <sequence>3</sequence>
            <sys_created_by>admin</sys_created_by>
            <sys_created_on>2017-01-26 20:14:39</sys_created_on>
            <sys_domain>global</sys_domain>
            <sys_domain_path>/</sys_domain_path>
            <sys_id>60b229350fa03200cd674f8ce1050eae</sys_id>
            <sys_mod_count>0</sys_mod_count>
            <sys_updated_by>admin</sys_updated_by>
            <sys_updated_on>2017-01-26 20:14:39</sys_updated_on>
            <value>16</value>
        </sys_choice>
        <sys_choice action="INSERT_OR_UPDATE">
            <dependent_value/>
            <element>state</element>
            <hint/>
            <inactive>false</inactive>
            <label>Closed Complete</label>
            <language>en</language>
            <name>x_58872_needit_needit</name>
            <sequence>4</sequence>
            <sys_created_by>admin</sys_created_by>
            <sys_created_on>2017-01-26 20:14:39</sys_created_on>
            <sys_domain>global</sys_domain>
            <sys_domain_path>/</sys_domain_path>
            <sys_id>a8b229350fa03200cd674f8ce1050eaf</sys_id>
            <sys_mod_count>0</sys_mod_count>
            <sys_updated_by>admin</sys_updated_by>
            <sys_updated_on>2017-01-26 20:14:39</sys_updated_on>
            <value>3</value>
        </sys_choice>
        <sys_choice action="INSERT_OR_UPDATE">
            <dependent_value/>
            <element>state</element>
            <hint/>
            <inactive>false</inactive>
            <label>Withdrawn</label>
            <language>en</language>
            <name>x_58872_needit_needit</name>
            <sequence>5</sequence>
            <sys_created_by>admin</sys_created_by>
            <sys_created_on>2017-01-26 20:14:39</sys_created_on>
            <sys_domain>global</sys_domain>
            <sys_domain_path>/</sys_domain_path>
            <sys_id>a0b229350fa03200cd674f8ce1050eb1</sys_id>
            <sys_mod_count>0</sys_mod_count>
            <sys_updated_by>admin</sys_updated_by>
            <sys_updated_on>2017-01-26 20:14:39</sys_updated_on>
            <value>8</value>
        </sys_choice>
        <sys_choice_set action="INSERT_OR_UPDATE">
            <element>state</element>
            <name>x_58872_needit_needit</name>
            <sys_class_name>sys_choice_set</sys_class_name>
            <sys_created_by>admin</sys_created_by>
            <sys_created_on>2017-01-26 20:14:39</sys_created_on>
            <sys_id>776049e5dbaf5b009d7831d0ef961901</sys_id>
            <sys_mod_count>1</sys_mod_count>
            <sys_name>state</sys_name>
            <sys_package display_value="NeedIt" source="x_58872_needit">6ead8e780f603200cd674f8ce1050ed1</sys_package>
            <sys_policy/>
            <sys_scope display_value="NeedIt">6ead8e780f603200cd674f8ce1050ed1</sys_scope>
            <sys_update_name>sys_choice_x_58872_needit_needit_state</sys_update_name>
            <sys_updated_by>admin</sys_updated_by>
            <sys_updated_on>2017-01-26 20:14:39</sys_updated_on>
        </sys_choice_set>
    </sys_choice>
</record_update>]]></payload>
        <payload_hash>-1231798200</payload_hash>
        <record_name>NeedIt.State</record_name>
        <reverted_from/>
        <source>86a64bfb2fd7541042ff4ae72799b696</source>
        <source_table>sys_upgrade_history</source_table>
        <state>previous</state>
        <sys_created_by>admin</sys_created_by>
        <sys_created_on>2020-09-24 02:39:03</sys_created_on>
        <sys_id>0db60ffb2fd7541042ff4ae72799b6f8</sys_id>
        <sys_mod_count>0</sys_mod_count>
        <sys_recorded_at>174bdfa7a8f0000001</sys_recorded_at>
        <sys_updated_by>admin</sys_updated_by>
        <sys_updated_on>2020-09-24 02:39:03</sys_updated_on>
        <type>Choice list</type>
        <update_guid>89b60ffb23d75410e7a270a078f442f8</update_guid>
        <update_guid_history>89b60ffb23d75410e7a270a078f442f8:0,3aa68bfb3dd75410e9a4ab2bc8e59872:1528579032,72a68bfb9dd75410417808ed8adfa36f:1886447883,7ea68bfb24d75410ea92f013c098d66b:-1196625253,7aa68bfbbdd75410e39aad8a6df64168:-1669741480,76a68bfb0ed75410d0f18ed6e1ea2265:775889921,72a68bfbd6d754106cf08c8cf31de662:-1246223066,b03ff6b7e1d7541075f0984fe8e3e701:0,4c3f76b7d1d754102240cfde7b3d82ce:1528579032,843f76b75fd75410ecaeda10cbd602cb:1886447883,803f76b7eed754103eb457e3687f06c8:-1196625253,8c3f76b736d7541039e852afaa3acbc4:-1669741480,883f76b7abd754106809528af0d1c0c1:775889921,843f76b785d7541085b9fea8f8008abe:-1246223066,e82af2b343d754108014abeed308d9ee:1528579032,242af2b363d754104dab0af733cf14eb:1886447883,202af2b3cad75410a818d6e91bbd62e8:-1196625253,2c2af2b33cd7541021f48c49b7e456e4:-1669741480,282af2b321d754105410a63fe95479e1:775889921,2c2af2b31dd7541057f53a39183ab5d1:-1246223066,7f9b2eb7aa97541097758abcff130276:0,d35b66b701975410699b734a690af1f5:1528579032,1f5b66b7bf975410132efed3146159f1:1886447883,1b5b66b737975410d8b6ee6e47317cee:-1196625253,175b66b7da97541070c23164f8a56aeb:-1669741480,135b66b7029754105f6e15ab65333ae8:775889921,db5b66b7ed975410d12fc2c3e2cf53e4:-1246223066,2108f283fe5bd010910c698de9ca587a:0,280872837d5bd010e0af6925c5e8cde7:1528579032,600872833c5bd01073463a7349f6e6e4:1886447883,5c0872830c5bd010d67d342f18ff57e0:-1196625253,58087283045bd01036d1e538080759dd:-1669741480,54087283d65bd0109ee14c1848adbeda:775889921,10087283b25bd0103c3975ee1627c1d7:-1246223066,5a42128bd9d7d01043ec270494cb4926:0,14d1964bc6d7d010103f2ff8a18af8fe:1528579032,d8d1964ba6d7d0105bb872b9f54917fa:1886447883,d4d1964be2d7d010e3bfc01fb956f8f7:-1196625253,c0d1964b78d7d010beb8fe52dcfb78f4:-1669741480,ccd1964bf4d7d010ef6a338070cac7f0:775889921,88d1964b24d7d0106f3e47b7333affed:-1246223066,9037ca8359d7d0103f0a275275185ca3:-1617139336</update_guid_history>
    </sys_update_version>
    <sys_metadata_delete action="INSERT_OR_UPDATE">
        <sys_audit_delete/>
        <sys_class_name>sys_metadata_delete</sys_class_name>
        <sys_created_by>admin</sys_created_by>
        <sys_created_on>2020-09-24 02:56:27</sys_created_on>
        <sys_db_object display_value="" name="sys_choice_set">sys_choice_set</sys_db_object>
        <sys_id>8db60ffb2fd7541042ff4ae72799b6e1</sys_id>
        <sys_metadata>8db60ffb2fd7541042ff4ae72799b6e1</sys_metadata>
        <sys_mod_count>0</sys_mod_count>
        <sys_name>state</sys_name>
        <sys_package display_value="NeedIt" source="x_58872_needit">6ead8e780f603200cd674f8ce1050ed1</sys_package>
        <sys_parent/>
        <sys_policy/>
        <sys_scope display_value="NeedIt">6ead8e780f603200cd674f8ce1050ed1</sys_scope>
        <sys_scope_delete display_value="">94872a8897db403e8ee69a431de2fca4</sys_scope_delete>
        <sys_update_name>sys_choice_x_58872_needit_needit_state</sys_update_name>
        <sys_update_version display_value="sys_choice_x_58872_needit_needit_state">0db60ffb2fd7541042ff4ae72799b6f8</sys_update_version>
        <sys_updated_by>admin</sys_updated_by>
        <sys_updated_on>2020-09-24 02:56:27</sys_updated_on>
    </sys_metadata_delete>
</record_update>
